structify/__init__.py
structify/cli.py
structify/generator.py
structify_cli-0.1.0.dist-info/METADATA
structify_cli-0.1.0.dist-info/WHEEL
structify_cli-0.1.0.dist-info/entry_points.txt
structify_cli-0.1.0.dist-info/top_level.txt
structify_cli-0.1.0.dist-info/RECORD
