Metadata-Version: 2.2
Name: structify-cli
Version: 0.1.0
Summary: A CLI tool to quickly generate project structures.
Author-email: Ameer Hamza Khan <your-email@example.com>
License: MIT
